cwsearch_utils/__init__.py
cwsearch_utils/aggregate.py
cwsearch_utils/infinstor_dbutils.py
cwsearch_utils/infinstor_lock.py
cwsearch_utils-0.1.75.dist-info/METADATA
cwsearch_utils-0.1.75.dist-info/WHEEL
cwsearch_utils-0.1.75.dist-info/top_level.txt
cwsearch_utils-0.1.75.dist-info/RECORD
