Metadata-Version: 2.1
Name: cwsearch-utils
Version: 0.1.75
Summary: InfinStor InfinLogs CloudWatch Search Utilities
Home-page: https://infinstor.com/
Author: InfinStor, Inc.
Author-email: support@infinstor.com
License: AGPL-3.0
Classifier: Programming Language :: Python :: 3
Classifier: License :: OSI Approved :: GNU Affero General Public License v3 or later (AGPLv3+)
Classifier: Operating System :: OS Independent
Requires-Python: >=3.7
Requires-Dist: boto3
Requires-Dist: arnparse
